llm_1min.py
llm_1min-0.1.4.dist-info/licenses/LICENSE
llm_1min-0.1.4.dist-info/METADATA
llm_1min-0.1.4.dist-info/WHEEL
llm_1min-0.1.4.dist-info/entry_points.txt
llm_1min-0.1.4.dist-info/top_level.txt
llm_1min-0.1.4.dist-info/RECORD
