Metadata-Version: 2.4
Name: llm-1min
Version: 0.1.4
Summary: LLM access to models served by 1minAI
Author: Sasa Cetkovic
License: Apache-2.0
Project-URL: Homepage, https://github.com/SasaCetkovic/llm-1min
Project-URL: Changelog, https://github.com/SasaCetkovic/llm-1min/releases
Project-URL: Issues, https://github.com/SasaCetkovic/llm-1min/issues
Project-URL: CI, https://github.com/SasaCetkovic/llm-1min/actions
Classifier: License :: OSI Approved :: Apache Software License
License-File: LICENSE
Requires-Dist: llm
Requires-Dist: requests
Dynamic: license-file
